[
   {
      "Title":"အမေရိကန်သမ္မတတို့ရဲ့ဟာသများ",
      "Author":"ခင်မောင်တိုးမိုးမိတ်",
      "Photo":"https://www.dropbox.com/scl/fi/v0ge7xlu0ygu2in7mdaaa/.jpg?rlkey=ocalp746d2mrzt3yt7lbg26xu&dl=1",
      "Link":"https://drive.google.com/file/d/1l280LYNHJJD-tsdNBX07efhe9rboZzJY/view?usp=drivesdk",
      "Des":""
   },
   {
      "Title":"အမှုအခင်းရှေ့နေနှင့်တရားခွင်ဟာသများ",
      "Author":"ဦးကျော်ဇေယျ",
      "Photo":"https://www.dropbox.com/scl/fi/ix1u4u2mirgx10gqodfcr/.jpg?rlkey=e6h780qrrd9xnq13e69w9sb34&dl=1",
      "Link":"https://drive.google.com/file/d/1Fv4QHMgdbZ80k-UNdmvObedxkoGbvyY4/view?usp=drivesdk",
      "Des":""
   },
   {
      "Title":"မဖဲဝါကျောက်ရုပ်",
      "Author":"တာတေ",
      "Photo":"https://www.dropbox.com/scl/fi/u7gregdxzqclmktly08ow/_.jpg?rlkey=n3ao5eccz7ore6lnone7bf7al&dl=1",
      "Link":"https://drive.google.com/file/d/19HBGdCm5Cn4Hpxk0m3O68biPH06-8WT5/view?usp=drivesdk",
      "Des":""
   },
   {
      "Title":"သိပ္ပံနည်းကျတွေးခေါ်မှု",
      "Author":"ခင်မောင်သန်း",
      "Photo":"https://www.dropbox.com/scl/fi/d4j7r5ym17s0ggfvghvaa/_.jpg?rlkey=q4h90c52y0zm30ax3icluqek4&dl=1",
      "Link":"https://drive.google.com/file/d/1BACnmi_3KUY6wVH3XbbrBuNxjj19VK8T/view?usp=drivesdk",
      "Des":""
   },
   {
      "Title":"ကလေးပုံပြင်များ",
      "Author":"မင်းသု၀ဏ်",
      "Photo":"https://www.dropbox.com/scl/fi/zft4ry87wugcluxbdnm5i/_.jpg?rlkey=i7m1jc3xn1t8qm736oll73vfg&dl=1",
      "Link":"https://drive.google.com/file/d/1bx6NyvClq6pYJ-zQk8MN7U-AH3Qpmya7/view?usp=drivesdk",
      "Des":""
   },
   {
      "Title":"သူငယ်ချင်းလို့ပဲဆက်၍ခေါ်မည်ခိုင်",
      "Author":"တက္ကသိုလ်ဘုန်းနိုင်",
      "Photo":"https://www.dropbox.com/scl/fi/3a20gcwq3i455gej0ntic/.jpg?rlkey=hfbo89glkihdux29ccvn5knqo&dl=1",
      "Link":"https://drive.google.com/file/d/1omoHLIjugFvrBI6a7ZXJfFDauDfZMfPb",
      "Des":""
   },
   {
      "Title":"သူ့ကျွန်မခံပြီ",
      "Author":"တက္ကသိုလ်ဘုန်းနိုင်",
      "Photo":"https://www.dropbox.com/scl/fi/1xuod5qwpqfjmcm0gmnr3/.jpg?rlkey=bzockk4lzk13p1jp75mpinqwu&dl=1",
      "Link":"https://drive.google.com/file/d/1OCOvlAEoCZV_dhG6lL9Z2ZFZ_3unbUj-/view?usp=drivesdk",
      "Des":""
   },
   {
      "Title":"ရှားလော့ဟုမ်း နှင့် ကျိန်စာသင့်အိမ်",
      "Author":"မောင်မြတ်မိုး",
      "Photo":"https://www.dropbox.com/scl/fi/ow2hxo5w039dr98yv42u5/.jpg?rlkey=mgorhaq35y1wxe874b28norac&dl=1",
      "Link":"https://drive.google.com/file/d/15lKZ4XAWpWjKnt6TfvJjoK-CGXlUVHdG/view?usp=drivesdk",
      "Des":""
   },
   {
      "Title":"အမေနှင့်အမေ့အကြောင်း",
      "Author":"ချစ်စံဝင်း",
      "Photo":"https://www.dropbox.com/scl/fi/zb65quchvvef0h2kdhhjr/.jpg?rlkey=4kfndqkcxgj4osd4f445pcnwg&dl=1",
      "Link":"https://drive.google.com/file/d/1d6LKoid9jOU58zggfweWC51sMfL8raDf/view?usp=drivesdk",
      "Des":""
   },
   {
      "Title":"ဖိုမဆက်ဆံရေး",
      "Author":"ဒေါက်တာအောင်ခင်ဆင့်",
      "Photo":"https://www.dropbox.com/scl/fi/n5bwutbtyrfqnfis5aphk/.jpg?rlkey=dz0508848nr4ibobgs2pnjzsr&dl=1",
      "Link":"https://drive.google.com/file/d/1sZhYvt4tFhrixQjAaZnGLkI42uGdCmFW/view?usp=drivesdk",
      "Des":""
   },
   {
      "Title":"သေခြင်း နှင့် အားမာန်",
      "Author":"လေသူရဲတစ်ဦး",
      "Photo":"https://www.dropbox.com/scl/fi/unz85uho2d3kpkfgxtezp/.jpg?rlkey=o1e6409w11bdb2qa5lr1rnznh&dl=1",
      "Link":"https://drive.google.com/file/d/1hxu_AA18RGmuxYmX6vYQr6KUrAhyUB-e/view?usp=drivesdk",
      "Des":""
   },
   {
      "Title":"အနေခက်အောင် ကူညီကြသူများ",
      "Author":"နန္ဒာသိန်းဇံ",
      "Photo":"https://www.dropbox.com/scl/fi/2ivb3non401o622m0xkwz/.jpg?rlkey=wsjpyyb4axxes8va1zhjhg38w&dl=1",
      "Link":"https://drive.google.com/file/d/13XMfzcudsBXURb46s3u3tj21hnI_8bcQ/view?usp=drivesdk",
      "Des":""
   },
   {
      "Title":"စောင့်နေသူ",
      "Author":"သတိုးတေဇ",
      "Photo":"https://www.dropbox.com/scl/fi/e3144f3jb15d1qbttcvtf/.jpg?rlkey=n1tgq4ihgg7ojdpi1eidqf9mm&dl=1",
      "Link":"https://drive.google.com/file/d/1Y0dWl09OnreMyuZx7KLYyEg0ZFb3qR0T/view?usp=drivesdk",
      "Des":""
   },
   {
      "Title":"ကြီးပွါးအောင်မြင် လွယ်ကူရိုးရှင်း လျှို့ဝှက်နည်း ၁၀၀",
      "Author":"သုခသိုက်",
      "Photo":"https://www.dropbox.com/scl/fi/z0feyykirow6q82ie4nsx/.jpg?rlkey=pge0ecptjvdp7q14xb002e1cs&dl=1",
      "Link":"https://drive.google.com/file/d/1cgt83Jrn1IM9ud9bBEUcbt42ko3Ye9LR/view?usp=drivesdk",
      "Des":""
   },
   {
      "Title":"ငွေရှာနည်းအနှစ်သာရများ",
      "Author":"ဆရာဦးမိုးမြင့်",
      "Photo":"https://www.dropbox.com/scl/fi/4uv6dothi0wuhw5017tiu/.jpg?rlkey=iwnw7ok3r88nbvap4xpd2w8i9&dl=1",
      "Link":"https://drive.google.com/file/d/174V-nuWcWbi6CZm83kVfFy43-wwxkp_H/view?usp=drivesdk",
      "Des":""
   },
   {
      "Title":"မင်းဘာသိလို့လဲ",
      "Author":"မင်းသိင်္ခ",
      "Photo":"https://www.dropbox.com/scl/fi/71180m3fvaord7rzpo4qd/.jpg?rlkey=h9y8bc0a0g1z2mqu02dswy8vi&dl=1",
      "Link":"https://drive.google.com/file/d/1J3eNJjT3iFiPHMPe7YfU216ikaTYNbZK/view?usp=drivesdk",
      "Des":""
   },
   {
      "Title":"သူငယ်ချင်းတစ်ယောက်အကြောင်း",
      "Author":"မင်းလူ",
      "Photo":"https://www.dropbox.com/scl/fi/yjgjjt2o3u0sr99cpu1km/.jpg?rlkey=0t2qxrqfmi3h5giiruide7kx8&dl=1",
      "Link":"https://drive.google.com/file/d/1EYGRr4812cu2Ff3XbKAH0ydho2GEU1mr/view?usp=drivesdk",
      "Des":""
   },
   {
      "Title":"ဟိုချီမင်း",
      "Author":"လင်းယုန်မောင်မောင်",
      "Photo":"https://www.dropbox.com/scl/fi/8gm1szn7w53t0uhskucow/.jpg?rlkey=m1cm91vja389qvrkns190ndyu&dl=1",
      "Link":"https://drive.google.com/file/d/1iUdepu2ToEmPj2R7hyLYy2xXm9dnPFix",
      "Des":""
   },
   {
      "Title":"အိပ်မက်ကမ္ဘာထဲ ပို့ဆောင်သူ",
      "Author":"မြတ်သက်",
      "Photo":"https://www.dropbox.com/scl/fi/umwkridqh26utpwlqynl9/.jpg?rlkey=s1b6tx11nw0mehon8v2wklaww&dl=1",
      "Link":"https://drive.google.com/file/d/1_hlAr-GgdIyZ5UyJt1vxiNf-NKDrRkx5/view?usp=drivesdk",
      "Des":""
   },
   {
      "Title":"ဘီလ်ဂိတ်ဆောက်တဲ့ဘဝအိမ်",
      "Author":"ကျော်ဇောဟိန်း(ဘာသာပြန်)",
      "Photo":"https://www.dropbox.com/scl/fi/74uz99rnsfjocr6pz64w0/.jpg?rlkey=jukhjjjuu1bd41f5dnzjjx5e7&dl=1",
      "Link":"https://drive.google.com/file/d/1nr7iXg6aR5SvazYRftoSqYpmdbktq20F/view?usp=drivesdk",
      "Des":""
   },
   {
      "Title":"အဆိပ်",
      "Author":"ထိန်လင်း",
      "Photo":"https://www.dropbox.com/scl/fi/g1cy5rzh408wku6sfm6ko/.jpg?rlkey=gx32jm2yiyydjbddrlwavf745&dl=1",
      "Link":"https://drive.google.com/file/d/1RIV4YzCK8VyzOKyiGdOeYmDLw-g60t1v/view?usp=drivesdk",
      "Des":""
   }
]
