[
   {
      "Title":"ခံတက်နုလေးတွေချိုးချိန်တန်တော့",
      "Author":"မိုးမိုး အင်းလျား",
      "Photo":"https://www.dropbox.com/scl/fi/f8qi52wokivk7h7wtponk/_.jpg?rlkey=oi6q33kndvro96ahcqi11ror3&st=0xxj2yac&dl=1",
      "Link":"https://drive.google.com/file/d/1OjFNRJWeXny5U4rwjswkGWV8mjj3cYHl/view?usp=drivesdk",
      "Des":"   "
   },
   {
      "Title":"နာမကျန်းသည်အိုနှင်းဆီ",
      "Author":"မိုးမိုး အင်းလျား",
      "Photo":"https://www.dropbox.com/scl/fi/wshtflkna0pwxxk3zocx5/_.jpg?rlkey=3d3tpgub3zra6g5u0kckzmclq&st=eppd8kf2&dl=1",
      "Link":"https://drive.google.com/file/d/1JAJRvsKUGKkLFMGqlAHRyNGLKEKmHcMu/view?usp=drivesdk",
      "Des":"   "
   },
   {
      "Title":"ညီမလေးကအချစ်ကိုကိုးကွယ်သတဲ့လား",
      "Author":"မိုးမိုး အင်းလျား",
      "Photo":"https://www.dropbox.com/scl/fi/z4t2dur5kbnthbde2w4ss/_.jpg?rlkey=i41c8o8mgjqucwlopgturfmsy&st=z4zprtc5&dl=1",
      "Link":"https://drive.google.com/file/d/1nW93YIu2ttkGgnxauQ0FGEnHzjM77-Uc/view?usp=drivesdk",
      "Des":"   "
   },
   {
      "Title":"ဝတ္ထုတိုများ၄",
      "Author":"မိုးမိုး အင်းလျား",
      "Photo":"https://www.dropbox.com/scl/fi/e3dxk5bh1owg7hm5zij9y/_.jpg?rlkey=a87em4vti2q9ecosdkvo9on7o&st=ekyw7i4g&dl=1",
      "Link":"https://drive.google.com/file/d/1yb1P1RMpbJ1icZe9JbY6YWpY5wqHWZby/view?usp=drivesdk",
      "Des":"   "
   },
   {
      "Title":"မသုဓမ္မစာရီ",
      "Author":"မိုးမိုး အင်းလျား",
      "Photo":"https://www.dropbox.com/scl/fi/xkwz204y6macqnlhyoj6z/_.jpg?rlkey=52c2rrsbfcjgg5dt1f54jpem8&st=9w6k2xnz&dl=1",
      "Link":"https://drive.google.com/file/d/1JQmc859tdoVhuhuLDHcXljW8OpszYNo6/view?usp=drivesdk",
      "Des":"   "
   },
   {
      "Title":"ကြွေမလိုနဲ့ဝေ_ဝေမလိုနဲ့ကြွေ",
      "Author":"မိုးမိုး အင်းလျား",
      "Photo":"https://www.dropbox.com/scl/fi/3acfq5ho2g90pehwiywk6/_-_.jpg?rlkey=pqmy9n7nfpj4bm72aj6xe4wjy&st=jozkajnt&dl=1",
      "Link":"https://drive.google.com/file/d/1XFHLzoFlDuLJVGKl6h3nYA6Fqi5N4zI2/view?usp=drivesdk",
      "Des":"   "
   },
   {
      "Title":"မေတ္တာကမ်းနားအချစ်သစ်ပင်",
      "Author":"မိုးမိုး အင်းလျား",
      "Photo":"https://www.dropbox.com/scl/fi/k5087x3gfyptdgivnhihe/_.jpg?rlkey=v7bxq605cfvz9pjqnbklpycvi&st=lrobwbm9&dl=1",
      "Link":"https://drive.google.com/file/d/1Yk0L9oGEEiUTSIWAneMv0XCKB_c5pB4Y/view?usp=drivesdk",
      "Des":"   "
   },
   {
      "Title":"ရွှေတိဂုံကိုမြင်လျှင်",
      "Author":"မိုးမိုး အင်းလျား",
      "Photo":"https://www.dropbox.com/scl/fi/i56ihy8bt80hn6khcllcr/.jpg?rlkey=yofz1019z2yk3qtyovbo7bmss&st=5eo2duh0&dl=1",
      "Link":"https://drive.google.com/file/d/1iJ0rMI_JKbdsZTyBpG2WxhAfQR_SaCfr/view?usp=drivesdk",
      "Des":"   "
   },
   {
      "Title":"ဘယ်သူလာကူပါ့မယ်",
      "Author":"မိုးမိုး အင်းလျား",
      "Photo":"https://www.dropbox.com/scl/fi/zme4qak20fjbnoks5nf6z/_.jpg?rlkey=526w4kk7t3ejct3gcj9f0bheg&st=njcikup4&dl=1",
      "Link":"https://drive.google.com/file/d/1xHPYa71b4C9xjHzO_LokmVJ1vcbtnEb7/view?usp=drivesdk",
      "Des":"   "
   },
   {
      "Title":"ပျောက်သောလမ်းမှာစမ်းတဝါး",
      "Author":"မိုးမိုး အင်းလျား",
      "Photo":"https://www.dropbox.com/scl/fi/48tsjc6b1pf2yhgcq4rk4/_.jpg?rlkey=aa0v1f7kfh0cl1h8d32zdxpd9&st=voy5x61f&dl=1",
      "Link":"https://drive.google.com/file/d/1mMZx2Z4T1V9k3hhPf63bJkI0C1wCTZoj/view?usp=drivesdk",
      "Des":"   "
   },
   {
      "Title":"ငြိမ်းကိုရှက်ပါ",
      "Author":"မိုးမိုး အင်းလျား",
      "Photo":"https://www.dropbox.com/scl/fi/b70m2gv1t47tba0ll5x9h/.jpg?rlkey=9mac2etbzad00qf0gxbo3z69g&st=rlbzwk2v&dl=1",
      "Link":"https://drive.google.com/file/d/1nAn9XJO-ZGW9xq0Zns731s-o5Un3Ocj4/view?usp=drivesdk",
      "Des":"   "
   }
]
