[
  {  

    
     "mainName":" Online Library",
    "Categories":" Categories",
    "newBook":" Newly added Books ",
    "Trending":" Trending Books",
    "Collections":" Best Collections",
    "mayLike":" Books you mayLike",
    "englishBook":" English Books",

"announce":"https://raw.githubusercontent.com/Bankhym/Sawlai/main/Others/announce.json",

    

    "maintenance":"No",
    "Categories-hide":"no",
    "newBook-hide":"No",
    "Trending-hide":"No",
    "Collections-hide":"no",
    "mayLike-hide":"No",
    "englishBook-hide":"No"

  }
]
